discountlib2/__init__.py
discountlib2/discountlib.py
discntss-0.1.0.dist-info/METADATA
discntss-0.1.0.dist-info/WHEEL
discntss-0.1.0.dist-info/top_level.txt
discntss-0.1.0.dist-info/RECORD
