Metadata-Version: 2.1
Name: discntss
Version: 0.1.0
Summary: A library for applying discounts to orders in a cloud kitchen Django application
Author: Meerath Nida Aman
Author-email: nidaaman77@gmail.com
Classifier: Development Status :: 3 - Alpha
Classifier: Intended Audience :: Developers
Classifier: License :: OSI Approved :: MIT License
Classifier: Programming Language :: Python :: 3
Classifier: Programming Language :: Python :: 3.6
Classifier: Programming Language :: Python :: 3.7
Classifier: Programming Language :: Python :: 3.8
Classifier: Programming Language :: Python :: 3.9
Requires-Dist: django (>=3.0)
